{"make": ["ACURA", "ALFA ROMEO", "ASTON MARTIN", "AUDI", "AZURE DYNAMICS", "BENTLEY", "BMW", "BRIGHTDROP", "CADILLAC", "CHEVROLET", "CHRYSLER", "DODGE", "FIAT", "FISKER", "FORD", "GENESIS", "GMC", "HONDA", "HYUNDAI", "JAGUAR", "JEEP", "KIA", "LAMBORGHINI", "LAND ROVER", "LEXUS", "LINCOLN", "LUCID", "MASERATI", "MAZDA", "MERCEDES-BENZ", "MINI", "MITSUBISHI", "MULLEN AUTOMOTIVE INC.", "NISSAN", "POLESTAR", "PORSCHE", "RAM", "RIVIAN", "ROLLS-ROYCE", "SMART", "SUBARU", "TESLA", "TH!NK", "TOYOTA", "VINFAST", "VOLKSWAGEN", "VOLVO", "WHEEGO ELECTRIC CARS"], "make_model_map": {"ACURA": ["ZDX"], "ALFA ROMEO": ["TONALE"], "ASTON MARTIN": ["VALHALLA"], "AUDI": ["A3", "A6", "A7 E", "A8 E", "E-TRON", "E-TRON GT", "E-TRON SPORTBACK", "Q4", "Q5", "Q5 E", "Q6", "Q8", "RS E-TRON GT", "S E-TRON GT", "S6", "SQ6", "SQ8"], "AZURE DYNAMICS": ["TRANSIT CONNECT ELECTRIC"], "BENTLEY": ["BENTAYGA", "CONTINENTAL", "FLYING SPUR"], "BMW": ["330E", "530E", "550E", "740E", "745E", "745LE", "750E", "I3", "I4", "I5", "I7", "I8", "IX", "M5", "X3", "X5", "XM"], "BRIGHTDROP": ["ZEVO"], "CADILLAC": ["CT6", "ELR", "LYRIQ", "OPTIQ", "VISTIQ"], "CHEVROLET": ["BLAZER", "BOLT", "BOLT EUV", "BOLT EV", "BRIGHTDROP", "EQUINOX", "SILVERADO", "SPARK", "VOLT"], "CHRYSLER": ["PACIFICA"], "DODGE": ["CHARGER", "HORNET"], "FIAT": ["500", "500E"], "FISKER": ["KARMA", "OCEAN"], "FORD": ["C-MAX", "ESCAPE", "F-150", "FOCUS", "FUSION", "MUSTANG MACH-E", "RANGER", "TRANSIT"], "GENESIS": ["G80", "GV60", "GV70"], "GMC": ["HUMMER EV PICKUP", "HUMMER EV SUV", "SIERRA"], "HONDA": ["ACCORD", "CLARITY", "PROLOGUE"], "HYUNDAI": ["IONIQ", "IONIQ 5", "IONIQ 5 N", "IONIQ 6", "IONIQ 9", "KONA", "SANTA FE", "SONATA", "TUCSON"], "JAGUAR": ["I-PACE"], "JEEP": ["GRAND CHEROKEE", "WAGONEER S", "WRANGLER"], "KIA": ["EV6", "EV9", "NIRO", "OPTIMA", "SORENTO", "SOUL", "SPORTAGE"], "LAMBORGHINI": ["REVUELTO", "URUS"], "LAND ROVER": ["RANGE ROVER", "RANGE ROVER SPORT"], "LEXUS": ["NX", "RX", "RZ", "TX"], "LINCOLN": ["AVIATOR", "CORSAIR"], "LUCID": ["AIR", "GRAVITY"], "MASERATI": ["GRANCABRIO"], "MAZDA": ["CX-70", "CX-90", "MX-30"], "MERCEDES-BENZ": ["AMG GT", "B-CLASS", "C-CLASS", "CLA-CLASS", "E-CLASS", "EQB-CLASS", "EQE-CLASS SEDAN", "EQE-CLASS SUV", "EQS-CLASS SEDAN", "EQS-CLASS SUV", "ESPRINTER", "G-CLASS", "GLC-CLASS", "GLE-CLASS", "S-CLASS", "SL-CLASS"], "MINI": ["COUNTRYMAN", "HARDTOP"], "MITSUBISHI": ["I-MIEV", "OUTLANDER"], "MULLEN AUTOMOTIVE INC.": ["ONE"], "NISSAN": ["ARIYA HATCHBACK", "ARIYA MPV", "LEAF"], "POLESTAR": ["POLESTAR 3", "POLESTAR 4", "PS2"], "PORSCHE": ["918", "CAYENNE", "MACAN", "PANAMERA", "TAYCAN"], "RAM": ["PROMASTER 3500"], "RIVIAN": ["EDV", "R1S", "R1T", "RCV"], "ROLLS-ROYCE": ["SPECTRE"], "SMART": ["EQ FORTWO", "FORTWO", "FORTWO ELECTRIC DRIVE"], "SUBARU": ["CROSSTREK", "SOLTERRA", "TRAILSEEKER", "UNCHARTED"], "TESLA": ["CYBERTRUCK", "MODEL 3", "MODEL S", "MODEL X", "MODEL Y", "ROADSTER"], "TH!NK": ["CITY"], "TOYOTA": ["BZ", "BZ WOODLAND", "BZ4X", "C-HR", "MIRAI", "PRIUS", "PRIUS PRIME (PHEV)", "RAV4", "RAV4 PRIME (PHEV)"], "VINFAST": ["VF 8"], "VOLKSWAGEN": ["E-GOLF", "ID. BUZZ", "ID.4"], "VOLVO": ["C40", "EX30", "EX30 CC", "EX40", "EX90", "S60", "S90", "V60", "XC40", "XC60", "XC90"], "WHEEGO ELECTRIC CARS": ["WHEEGO"]}, "electric_vehicle_type": ["Battery Electric Vehicle (BEV)", "Plug-in Hybrid Electric Vehicle (PHEV)"], "cafv_eligibility": ["Clean Alternative Fuel Vehicle Eligible", "Eligibility unknown as battery range has not been researched", "Not eligible due to low battery range"]}